LICENSE.txt
README.md
setup.cfg
setup.py
pytoolsml/__init__.py
pytoolsml/pytoolsml.py
pytoolsml.egg-info/PKG-INFO
pytoolsml.egg-info/SOURCES.txt
pytoolsml.egg-info/dependency_links.txt
pytoolsml.egg-info/top_level.txt