Metadata-Version: 2.1
Name: pytoolsml
Version: 2.0.3
Summary: Machine Learning wrapper for scaled prediction
Author: Collins
License: MIT
Classifier: Development Status :: 3 - Alpha
Classifier: Intended Audience :: Developers
Classifier: Topic :: Software Development :: Build Tools
Classifier: License :: OSI Approved :: MIT License
Classifier: Programming Language :: Python :: 3.6
License-File: LICENSE.txt
